apimyllama.py
apimyllama-1.0.0.dist-info/METADATA
apimyllama-1.0.0.dist-info/WHEEL
apimyllama-1.0.0.dist-info/top_level.txt
apimyllama-1.0.0.dist-info/RECORD
