Metadata-Version: 2.1
Name: apimyllama
Version: 1.0.0
Summary: A package for interacting with the APIMyLlama API
Author: Liam Vang
Author-email: gimerstudios@gmail.com
Classifier: Programming Language :: Python :: 3
Classifier: License :: OSI Approved :: MIT License
Classifier: Operating System :: OS Independent
Requires-Python: >=3.6
Requires-Dist: requests
